{"_env":"NODEJS","_serializationMethod":"normal","_autosave":false,"_autosaveInterval":5000,"_collections":[{"name":"items","unindexedSortComparator":"js","defaultLokiOperatorPackage":"js","_dynamicViews":[],"uniqueNames":[],"transforms":{},"rangedIndexes":{},"_data":[{"toc":[],"body":{"type":"root","children":[{"type":"element","tag":"p","props":{},"children":[{"type":"text","value":"[\n{\n\"title\": \"qweqweqwe\",\n\"years\": \"1234\"\n},\n{\n\"title\": \"asdfasdfasdf\",\n\"years\": \"14\"\n},\n{\n\"title\": \"zzzzzzzzzz\",\n\"years\": \"777\"\n},\n{\n\"title\": \"Aret\",\n\"years\": \"543\"\n},\n{\n\"title\": \"Cader\",\n\"years\": \"1998\"\n}\n]"}]}]},"text":"[\n    {\n        \"title\": \"qweqweqwe\",\n        \"years\": \"1234\"\n    },\n    {\n        \"title\": \"asdfasdfasdf\",\n        \"years\": \"14\"\n    },\n    {\n        \"title\": \"zzzzzzzzzz\",\n        \"years\": \"777\"\n    },\n    {\n        \"title\": \"Aret\",\n        \"years\": \"543\"\n    },\n    {\n        \"title\": \"Cader\",\n        \"years\": \"1998\"\n    }\n]","dir":"/","path":"/hello","extension":".md","slug":"hello","createdAt":"2021-02-08T13:41:28.471Z","updatedAt":"2021-02-08T13:41:28.471Z","meta":{"version":0,"revision":0,"created":1613573363860},"$loki":1},{"0":{"Title":"qweqweqwe","years":"1234"},"dir":"/test","path":"/test/test1","extension":".json","slug":"test1","createdAt":"2021-02-08T13:41:28.471Z","updatedAt":"2021-02-08T13:41:28.471Z","meta":{"version":0,"revision":0,"created":1613573363861},"$loki":2},{"0":{"title":"Cader","years":"1998"},"dir":"/test","path":"/test/test2","extension":".json","slug":"test2","createdAt":"2021-02-08T13:41:28.471Z","updatedAt":"2021-02-08T13:41:28.471Z","meta":{"version":0,"revision":0,"created":1613573363861},"$loki":3}],"idIndex":[1,2,3],"maxId":3,"_dirty":true,"_nestedProperties":[],"transactional":false,"asyncListeners":false,"disableMeta":false,"disableChangesApi":true,"disableDeltaChangesApi":true,"cloneObjects":false,"cloneMethod":"deep","changes":[],"_fullTextSearch":{"ii":{"title":{"_store":true,"_optimizeChanges":true,"docCount":0,"docStore":[],"totalFieldLength":0,"root":{}},"description":{"_store":true,"_optimizeChanges":true,"docCount":0,"docStore":[],"totalFieldLength":0,"root":{}},"slug":{"_store":true,"_optimizeChanges":true,"docCount":3,"docStore":[[0,{"fieldLength":1}],[1,{"fieldLength":1}],[2,{"fieldLength":1}]],"totalFieldLength":3,"root":{"k":[104,116],"v":[{"k":[101],"v":[{"k":[108],"v":[{"k":[108],"v":[{"k":[111],"v":[{"d":{"df":1,"dc":[[0,1]]}}]}]}]}]},{"k":[101],"v":[{"k":[115],"v":[{"k":[116],"v":[{"k":[49,50],"v":[{"d":{"df":1,"dc":[[1,1]]}},{"d":{"df":1,"dc":[[2,1]]}}]}]}]}]}]}},"text":{"_store":true,"_optimizeChanges":true,"docCount":1,"docStore":[[0,{"fieldLength":32}]],"totalFieldLength":32,"root":{"k":[91,123,34,125,93],"v":[{"d":{"df":1,"dc":[[0,1]]}},{"d":{"df":1,"dc":[[0,5]]}},{"k":[116,113,121,49,97,122,55,53,99],"v":[{"k":[105],"v":[{"k":[116],"v":[{"k":[108],"v":[{"k":[101],"v":[{"k":[34],"v":[{"k":[58],"v":[{"d":{"df":1,"dc":[[0,5]]}}]}]}]}]}]}]},{"k":[119],"v":[{"k":[101],"v":[{"k":[113],"v":[{"k":[119],"v":[{"k":[101],"v":[{"k":[113],"v":[{"k":[119],"v":[{"k":[101],"v":[{"k":[34],"v":[{"k":[44],"v":[{"d":{"df":1,"dc":[[0,1]]}}]}]}]}]}]}]}]}]}]}]},{"k":[101],"v":[{"k":[97],"v":[{"k":[114],"v":[{"k":[115],"v":[{"k":[34],"v":[{"k":[58],"v":[{"d":{"df":1,"dc":[[0,5]]}}]}]}]}]}]}]},{"k":[50,52,57],"v":[{"k":[51],"v":[{"k":[52],"v":[{"k":[34],"v":[{"d":{"df":1,"dc":[[0,1]]}}]}]}]},{"k":[34],"v":[{"d":{"df":1,"dc":[[0,1]]}}]},{"k":[57],"v":[{"k":[56],"v":[{"k":[34],"v":[{"d":{"df":1,"dc":[[0,1]]}}]}]}]}]},{"k":[115,114],"v":[{"k":[100],"v":[{"k":[102],"v":[{"k":[97],"v":[{"k":[115],"v":[{"k":[100],"v":[{"k":[102],"v":[{"k":[97],"v":[{"k":[115],"v":[{"k":[100],"v":[{"k":[102],"v":[{"k":[34],"v":[{"k":[44],"v":[{"d":{"df":1,"dc":[[0,1]]}}]}]}]}]}]}]}]}]}]}]}]}]},{"k":[101],"v":[{"k":[116],"v":[{"k":[34],"v":[{"k":[44],"v":[{"d":{"df":1,"dc":[[0,1]]}}]}]}]}]}]},{"k":[122],"v":[{"k":[122],"v":[{"k":[122],"v":[{"k":[122],"v":[{"k":[122],"v":[{"k":[122],"v":[{"k":[122],"v":[{"k":[122],"v":[{"k":[122],"v":[{"k":[34],"v":[{"k":[44],"v":[{"d":{"df":1,"dc":[[0,1]]}}]}]}]}]}]}]}]}]}]}]}]},{"k":[55],"v":[{"k":[55],"v":[{"k":[34],"v":[{"d":{"df":1,"dc":[[0,1]]}}]}]}]},{"k":[52],"v":[{"k":[51],"v":[{"k":[34],"v":[{"d":{"df":1,"dc":[[0,1]]}}]}]}]},{"k":[97],"v":[{"k":[100],"v":[{"k":[101],"v":[{"k":[114],"v":[{"k":[34],"v":[{"k":[44],"v":[{"d":{"df":1,"dc":[[0,1]]}}]}]}]}]}]}]}]},{"d":{"df":1,"dc":[[0,1]]},"k":[44],"v":[{"d":{"df":1,"dc":[[0,4]]}}]},{"d":{"df":1,"dc":[[0,1]]}}]}}}}}],"databaseVersion":1.5,"engineVersion":1.5,"filename":"content.db","_persistenceAdapter":null,"_persistenceMethod":null,"_throttledSaves":true}